Workbook

Sheet 📊 Resumen y Cotización
A1: SISTEMA INTEGRAL DE COTIZACIÓN - RESUMEN GENERAL
A3: Proyecto: | B3: Mobiliario Residencial Estándar | D3: Fecha: | E3: =TODAY()
A4: Cliente: | B4: Público General / Plantilla | D4: Moneda: | E4: MXN ($)
A6: COSTO MATERIALES (TABLEROS) | C6: COSTO HERRAJES Y ACCESORIOS | E6: COSTO CINTILLAS / CANTOS | G6: PRECIO FINAL SUGERIDO
A7: =SUMIF('📋 Explosión y Despiece'!E:E, "<>HERRAJE", '📋 Explosión y Despiece'!P4:P100) | C7: =SUMIF('📋 Explosión y Despiece'!E:E, "HERRAJE", '📋 Explosión y Despiece'!P4:P100) | E7: =SUM('📋 Explosión y Despiece'!R4:R100) | G7: =B18
A10: Estructura Financiera de la Cotización
A11: Concepto / Elemento de Costo | B11: Monto / Indicador | C11: Observaciones
A12: (+) Costo Total de Materiales (Tableros) | B12: =A7 | C12: Costo directo calculado por M² utilizado
A13: (+) Costo Total de Herrajes y Accesorios | B13: =C7 | C13: Costo directo por pieza o juego
A14: (+) Costo Total de Cintillas (Cantos) | B14: =E7 | C14: Costo directo por metros lineales de pegado
A15: (=) COSTO DIRECTO TOTAL | B15: =SUM(B12:B14) | C15: Suma total de insumos requeridos
A16: (×) Factor de Margen / Utilidad | B16: 1.35 | C16: Multiplicador de ganancia (35% de utilidad)
A17: (+) Costo de Mano de Obra / Fijo | B17: 1200 | C17: Armado, instalación y gastos fijos de taller
A18: (=) PRECIO DE VENTA FINAL | B18: =(B15*B16)+B17 | C18: Precio sugerido al cliente antes de IVA

Sheet 📋 Explosión y Despiece
A1: DETALLE DE EXPLOSIÓN, DESPIECE Y TRAZABILIDAD DE PRODUCCIÓN
A3: Cantidad | B3: Largo (mm) | C3: Ancho (mm) | D3: Descripción de la Pieza / Módulo | E3: Materia Prima | F3: Veta | G3: Largo 1 | H3: Largo 2 | I3: Ancho 1 | J3: Ancho 2 | K3: ID Módulo | L3: ID Pieza Único | M3: M² Totales | N3: ML Cintilla | O3: Costo Unit. Mat/Herr | P3: Costo Tot. Mat/Herr | Q3: Costo Unit. Cintilla | R3: Costo Tot. Cintilla | S3: Costo Total Elemento
A4: Gabinete 1 Puerta 300 x 720 x 590 mm [Código Módulo: MOD-GAB-01]
A5: 1 | B5: 720 | C5: 590 | D5: Costado Derecho | E5: ARAUCO BLANCO | F5: 0 | G5: 1 | H5: 1 | I5: 1 | J5: 1 | K5: MOD-GAB-01 | L5: MOD-GAB-01-P01 | M5: =IF(AND(ISNUMBER(B5), B5>0), (A5*B5*C5)/1000000, 0) | N5: =IF(AND(ISNUMBER(B5), B5>0), A5*(((G5+H5)*B5 + (I5+J5)*C5)/1000), 0) | O5: =IF(E5="HERRAJE", IFERROR(VLOOKUP(D5, '⚙️ Configuración Costos'!$A$13:$B$30, 2, FALSE), 0), IFERROR(VLOOKUP(E5, '⚙️ Configuración Costos'!$A$5:$B$10, 2, FALSE), 0)) | P5: =IF(E5="HERRAJE", A5*O5, M5*O5) | Q5: =IF(E5="HERRAJE", 0, IFERROR(VLOOKUP(E5, '⚙️ Configuración Costos'!$E$5:$F$10, 2, FALSE), 0)) | R5: =N5*Q5 | S5: =P5+R5
A6: 1 | B6: 720 | C6: 590 | D6: Costado Izquierdo | E6: ARAUCO BLANCO | F6: 0 | G6: 1 | H6: 1 | I6: 1 | J6: 1 | K6: MOD-GAB-01 | L6: MOD-GAB-01-P02 | M6: =IF(AND(ISNUMBER(B6), B6>0), (A6*B6*C6)/1000000, 0) | N6: =IF(AND(ISNUMBER(B6), B6>0), A6*(((G6+H6)*B6 + (I6+J6)*C6)/1000), 0) | O6: =IF(E6="HERRAJE", IFERROR(VLOOKUP(D6, '⚙️ Configuración Costos'!$A$13:$B$30, 2, FALSE), 0), IFERROR(VLOOKUP(E6, '⚙️ Configuración Costos'!$A$5:$B$10, 2, FALSE), 0)) | P6: =IF(E6="HERRAJE", A6*O6, M6*O6) | Q6: =IF(E6="HERRAJE", 0, IFERROR(VLOOKUP(E6, '⚙️ Configuración Costos'!$E$5:$F$10, 2, FALSE), 0)) | R6: =N6*Q6 | S6: =P6+R6
A7: 1 | B7: 689 | C7: 269 | D7: Respaldo Gabinete | E7: ARAUCO BLANCO | F7: 0 | G7: 0 | H7: 0 | I7: 0 | J7: 0 | K7: MOD-GAB-01 | L7: MOD-GAB-01-P03 | M7: =IF(AND(ISNUMBER(B7), B7>0), (A7*B7*C7)/1000000, 0) | N7: =IF(AND(ISNUMBER(B7), B7>0), A7*(((G7+H7)*B7 + (I7+J7)*C7)/1000), 0) | O7: =IF(E7="HERRAJE", IFERROR(VLOOKUP(D7, '⚙️ Configuración Costos'!$A$13:$B$30, 2, FALSE), 0), IFERROR(VLOOKUP(E7, '⚙️ Configuración Costos'!$A$5:$B$10, 2, FALSE), 0)) | P7: =IF(E7="HERRAJE", A7*O7, M7*O7) | Q7: =IF(E7="HERRAJE", 0, IFERROR(VLOOKUP(E7, '⚙️ Configuración Costos'!$E$5:$F$10, 2, FALSE), 0)) | R7: =N7*Q7 | S7: =P7+R7
A8: 1 | B8: 590 | C8: 269 | D8: Piso Gabinete | E8: ARAUCO BLANCO | F8: 0 | G8: 0 | H8: 0 | I8: 1 | J8: 1 | K8: MOD-GAB-01 | L8: MOD-GAB-01-P04 | M8: =IF(AND(ISNUMBER(B8), B8>0), (A8*B8*C8)/1000000, 0) | N8: =IF(AND(ISNUMBER(B8), B8>0), A8*(((G8+H8)*B8 + (I8+J8)*C8)/1000), 0) | O8: =IF(E8="HERRAJE", IFERROR(VLOOKUP(D8, '⚙️ Configuración Costos'!$A$13:$B$30, 2, FALSE), 0), IFERROR(VLOOKUP(E8, '⚙️ Configuración Costos'!$A$5:$B$10, 2, FALSE), 0)) | P8: =IF(E8="HERRAJE", A8*O8, M8*O8) | Q8: =IF(E8="HERRAJE", 0, IFERROR(VLOOKUP(E8, '⚙️ Configuración Costos'!$E$5:$F$10, 2, FALSE), 0)) | R8: =N8*Q8 | S8: =P8+R8
A9: 1 | B9: 520 | C9: 269 | D9: Entrepano Gabinete | E9: ARAUCO BLANCO | F9: 0 | G9: 0 | H9: 0 | I9: 0 | J9: 1 | K9: MOD-GAB-01 | L9: MOD-GAB-01-P05 | M9: =IF(AND(ISNUMBER(B9), B9>0), (A9*B9*C9)/1000000, 0) | N9: =IF(AND(ISNUMBER(B9), B9>0), A9*(((G9+H9)*B9 + (I9+J9)*C9)/1000), 0) | O9: =IF(E9="HERRAJE", IFERROR(VLOOKUP(D9, '⚙️ Configuración Costos'!$A$13:$B$30, 2, FALSE), 0), IFERROR(VLOOKUP(E9, '⚙️ Configuración Costos'!$A$5:$B$10, 2, FALSE), 0)) | P9: =IF(E9="HERRAJE", A9*O9, M9*O9) | Q9: =IF(E9="HERRAJE", 0, IFERROR(VLOOKUP(E9, '⚙️ Configuración Costos'!$E$5:$F$10, 2, FALSE), 0)) | R9: =N9*Q9 | S9: =P9+R9
A10: 1 | B10: 269 | C10: 120 | D10: Manguete Frontal | E10: ARAUCO BLANCO | F10: 0 | G10: 1 | H10: 1 | I10: 0 | J10: 0 | K10: MOD-GAB-01 | L10: MOD-GAB-01-P06 | M10: =IF(AND(ISNUMBER(B10), B10>0), (A10*B10*C10)/1000000, 0) | N10: =IF(AND(ISNUMBER(B10), B10>0), A10*(((G10+H10)*B10 + (I10+J10)*C10)/1000), 0) | O10: =IF(E10="HERRAJE", IFERROR(VLOOKUP(D10, '⚙️ Configuración Costos'!$A$13:$B$30, 2, FALSE), 0), IFERROR(VLOOKUP(E10, '⚙️ Configuración Costos'!$A$5:$B$10, 2, FALSE), 0)) | P10: =IF(E10="HERRAJE", A10*O10, M10*O10) | Q10: =IF(E10="HERRAJE", 0, IFERROR(VLOOKUP(E10, '⚙️ Configuración Costos'!$E$5:$F$10, 2, FALSE), 0)) | R10: =N10*Q10 | S10: =P10+R10
A11: 1 | B11: 269 | C11: 120 | D11: Manguete Posterior | E11: ARAUCO BLANCO | F11: 0 | G11: 1 | H11: 1 | I11: 0 | J11: 0 | K11: MOD-GAB-01 | L11: MOD-GAB-01-P07 | M11: =IF(AND(ISNUMBER(B11), B11>0), (A11*B11*C11)/1000000, 0) | N11: =IF(AND(ISNUMBER(B11), B11>0), A11*(((G11+H11)*B11 + (I11+J11)*C11)/1000), 0) | O11: =IF(E11="HERRAJE", IFERROR(VLOOKUP(D11, '⚙️ Configuración Costos'!$A$13:$B$30, 2, FALSE), 0), IFERROR(VLOOKUP(E11, '⚙️ Configuración Costos'!$A$5:$B$10, 2, FALSE), 0)) | P11: =IF(E11="HERRAJE", A11*O11, M11*O11) | Q11: =IF(E11="HERRAJE", 0, IFERROR(VLOOKUP(E11, '⚙️ Configuración Costos'!$E$5:$F$10, 2, FALSE), 0)) | R11: =N11*Q11 | S11: =P11+R11
A12: 1 | B12: 717 | C12: 296 | D12: Puerta Gabinete | E12: MADERADO FRENTE | F12: 1 | G12: 1 | H12: 1 | I12: 1 | J12: 1 | K12: MOD-GAB-01 | L12: MOD-GAB-01-P08 | M12: =IF(AND(ISNUMBER(B12), B12>0), (A12*B12*C12)/1000000, 0) | N12: =IF(AND(ISNUMBER(B12), B12>0), A12*(((G12+H12)*B12 + (I12+J12)*C12)/1000), 0) | O12: =IF(E12="HERRAJE", IFERROR(VLOOKUP(D12, '⚙️ Configuración Costos'!$A$13:$B$30, 2, FALSE), 0), IFERROR(VLOOKUP(E12, '⚙️ Configuración Costos'!$A$5:$B$10, 2, FALSE), 0)) | P12: =IF(E12="HERRAJE", A12*O12, M12*O12) | Q12: =IF(E12="HERRAJE", 0, IFERROR(VLOOKUP(E12, '⚙️ Configuración Costos'!$E$5:$F$10, 2, FALSE), 0)) | R12: =N12*Q12 | S12: =P12+R12
A13: 2 | B13: 0 | C13: 0 | D13: Bisagra Cierre Lento | E13: HERRAJE | F13: 0 | G13: 0 | H13: 0 | I13: 0 | J13: 0 | K13: MOD-GAB-01 | L13: MOD-GAB-01-H01 | M13: =IF(AND(ISNUMBER(B13), B13>0), (A13*B13*C13)/1000000, 0) | N13: =IF(AND(ISNUMBER(B13), B13>0), A13*(((G13+H13)*B13 + (I13+J13)*C13)/1000), 0) | O13: =IF(E13="HERRAJE", IFERROR(VLOOKUP(D13, '⚙️ Configuración Costos'!$A$13:$B$30, 2, FALSE), 0), IFERROR(VLOOKUP(E13, '⚙️ Configuración Costos'!$A$5:$B$10, 2, FALSE), 0)) | P13: =IF(E13="HERRAJE", A13*O13, M13*O13) | Q13: =IF(E13="HERRAJE", 0, IFERROR(VLOOKUP(E13, '⚙️ Configuración Costos'!$E$5:$F$10, 2, FALSE), 0)) | R13: =N13*Q13 | S13: =P13+R13
A14: 1 | B14: 0 | C14: 0 | D14: Jaladera Acero Inox | E14: HERRAJE | F14: 0 | G14: 0 | H14: 0 | I14: 0 | J14: 0 | K14: MOD-GAB-01 | L14: MOD-GAB-01-H02 | M14: =IF(AND(ISNUMBER(B14), B14>0), (A14*B14*C14)/1000000, 0) | N14: =IF(AND(ISNUMBER(B14), B14>0), A14*(((G14+H14)*B14 + (I14+J14)*C14)/1000), 0) | O14: =IF(E14="HERRAJE", IFERROR(VLOOKUP(D14, '⚙️ Configuración Costos'!$A$13:$B$30, 2, FALSE), 0), IFERROR(VLOOKUP(E14, '⚙️ Configuración Costos'!$A$5:$B$10, 2, FALSE), 0)) | P14: =IF(E14="HERRAJE", A14*O14, M14*O14) | Q14: =IF(E14="HERRAJE", 0, IFERROR(VLOOKUP(E14, '⚙️ Configuración Costos'!$E$5:$F$10, 2, FALSE), 0)) | R14: =N14*Q14 | S14: =P14+R14
A15: 4 | B15: 0 | C15: 0 | D15: Pata Regulable Plastica | E15: HERRAJE | F15: 0 | G15: 0 | H15: 0 | I15: 0 | J15: 0 | K15: MOD-GAB-01 | L15: MOD-GAB-01-H03 | M15: =IF(AND(ISNUMBER(B15), B15>0), (A15*B15*C15)/1000000, 0) | N15: =IF(AND(ISNUMBER(B15), B15>0), A15*(((G15+H15)*B15 + (I15+J15)*C15)/1000), 0) | O15: =IF(E15="HERRAJE", IFERROR(VLOOKUP(D15, '⚙️ Configuración Costos'!$A$13:$B$30, 2, FALSE), 0), IFERROR(VLOOKUP(E15, '⚙️ Configuración Costos'!$A$5:$B$10, 2, FALSE), 0)) | P15: =IF(E15="HERRAJE", A15*O15, M15*O15) | Q15: =IF(E15="HERRAJE", 0, IFERROR(VLOOKUP(E15, '⚙️ Configuración Costos'!$E$5:$F$10, 2, FALSE), 0)) | R15: =N15*Q15 | S15: =P15+R15
A16: 40 | B16: 0 | C16: 0 | D16: Tornillo 4x50 mm | E16: HERRAJE | F16: 0 | G16: 0 | H16: 0 | I16: 0 | J16: 0 | K16: MOD-GAB-01 | L16: MOD-GAB-01-H04 | M16: =IF(AND(ISNUMBER(B16), B16>0), (A16*B16*C16)/1000000, 0) | N16: =IF(AND(ISNUMBER(B16), B16>0), A16*(((G16+H16)*B16 + (I16+J16)*C16)/1000), 0) | O16: =IF(E16="HERRAJE", IFERROR(VLOOKUP(D16, '⚙️ Configuración Costos'!$A$13:$B$30, 2, FALSE), 0), IFERROR(VLOOKUP(E16, '⚙️ Configuración Costos'!$A$5:$B$10, 2, FALSE), 0)) | P16: =IF(E16="HERRAJE", A16*O16, M16*O16) | Q16: =IF(E16="HERRAJE", 0, IFERROR(VLOOKUP(E16, '⚙️ Configuración Costos'!$E$5:$F$10, 2, FALSE), 0)) | R16: =N16*Q16 | S16: =P16+R16
A17: 4 | B17: 0 | C17: 0 | D17: Soporte de Entrepaño | E17: HERRAJE | F17: 0 | G17: 0 | H17: 0 | I17: 0 | J17: 0 | K17: MOD-GAB-01 | L17: MOD-GAB-01-H05 | M17: =IF(AND(ISNUMBER(B17), B17>0), (A17*B17*C17)/1000000, 0) | N17: =IF(AND(ISNUMBER(B17), B17>0), A17*(((G17+H17)*B17 + (I17+J17)*C17)/1000), 0) | O17: =IF(E17="HERRAJE", IFERROR(VLOOKUP(D17, '⚙️ Configuración Costos'!$A$13:$B$30, 2, FALSE), 0), IFERROR(VLOOKUP(E17, '⚙️ Configuración Costos'!$A$5:$B$10, 2, FALSE), 0)) | P17: =IF(E17="HERRAJE", A17*O17, M17*O17) | Q17: =IF(E17="HERRAJE", 0, IFERROR(VLOOKUP(E17, '⚙️ Configuración Costos'!$E$5:$F$10, 2, FALSE), 0)) | R17: =N17*Q17 | S17: =P17+R17
A18: Cajonera 4 Cajones 500 x 720 x 590 mm [Código Módulo: MOD-CAJ-01]
A19: 1 | B19: 720 | C19: 590 | D19: Costado Derecho | E19: ARAUCO BLANCO | F19: 0 | G19: 1 | H19: 1 | I19: 1 | J19: 1 | K19: MOD-CAJ-01 | L19: MOD-CAJ-01-P01 | M19: =IF(AND(ISNUMBER(B19), B19>0), (A19*B19*C19)/1000000, 0) | N19: =IF(AND(ISNUMBER(B19), B19>0), A19*(((G19+H19)*B19 + (I19+J19)*C19)/1000), 0) | O19: =IF(E19="HERRAJE", IFERROR(VLOOKUP(D19, '⚙️ Configuración Costos'!$A$13:$B$30, 2, FALSE), 0), IFERROR(VLOOKUP(E19, '⚙️ Configuración Costos'!$A$5:$B$10, 2, FALSE), 0)) | P19: =IF(E19="HERRAJE", A19*O19, M19*O19) | Q19: =IF(E19="HERRAJE", 0, IFERROR(VLOOKUP(E19, '⚙️ Configuración Costos'!$E$5:$F$10, 2, FALSE), 0)) | R19: =N19*Q19 | S19: =P19+R19
A20: 1 | B20: 720 | C20: 590 | D20: Costado Izquierdo | E20: ARAUCO BLANCO | F20: 0 | G20: 1 | H20: 1 | I20: 1 | J20: 1 | K20: MOD-CAJ-01 | L20: MOD-CAJ-01-P02 | M20: =IF(AND(ISNUMBER(B20), B20>0), (A20*B20*C20)/1000000, 0) | N20: =IF(AND(ISNUMBER(B20), B20>0), A20*(((G20+H20)*B20 + (I20+J20)*C20)/1000), 0) | O20: =IF(E20="HERRAJE", IFERROR(VLOOKUP(D20, '⚙️ Configuración Costos'!$A$13:$B$30, 2, FALSE), 0), IFERROR(VLOOKUP(E20, '⚙️ Configuración Costos'!$A$5:$B$10, 2, FALSE), 0)) | P20: =IF(E20="HERRAJE", A20*O20, M20*O20) | Q20: =IF(E20="HERRAJE", 0, IFERROR(VLOOKUP(E20, '⚙️ Configuración Costos'!$E$5:$F$10, 2, FALSE), 0)) | R20: =N20*Q20 | S20: =P20+R20
A21: 1 | B21: 590 | C21: 469 | D21: Piso Gabinete | E21: ARAUCO BLANCO | F21: 0 | G21: 0 | H21: 0 | I21: 1 | J21: 1 | K21: MOD-CAJ-01 | L21: MOD-CAJ-01-P03 | M21: =IF(AND(ISNUMBER(B21), B21>0), (A21*B21*C21)/1000000, 0) | N21: =IF(AND(ISNUMBER(B21), B21>0), A21*(((G21+H21)*B21 + (I21+J21)*C21)/1000), 0) | O21: =IF(E21="HERRAJE", IFERROR(VLOOKUP(D21, '⚙️ Configuración Costos'!$A$13:$B$30, 2, FALSE), 0), IFERROR(VLOOKUP(E21, '⚙️ Configuración Costos'!$A$5:$B$10, 2, FALSE), 0)) | P21: =IF(E21="HERRAJE", A21*O21, M21*O21) | Q21: =IF(E21="HERRAJE", 0, IFERROR(VLOOKUP(E21, '⚙️ Configuración Costos'!$E$5:$F$10, 2, FALSE), 0)) | R21: =N21*Q21 | S21: =P21+R21
A22: 1 | B22: 689 | C22: 469 | D22: Respaldo Gabinete | E22: ARAUCO BLANCO | F22: 0 | G22: 0 | H22: 0 | I22: 0 | J22: 0 | K22: MOD-CAJ-01 | L22: MOD-CAJ-01-P04 | M22: =IF(AND(ISNUMBER(B22), B22>0), (A22*B22*C22)/1000000, 0) | N22: =IF(AND(ISNUMBER(B22), B22>0), A22*(((G22+H22)*B22 + (I22+J22)*C22)/1000), 0) | O22: =IF(E22="HERRAJE", IFERROR(VLOOKUP(D22, '⚙️ Configuración Costos'!$A$13:$B$30, 2, FALSE), 0), IFERROR(VLOOKUP(E22, '⚙️ Configuración Costos'!$A$5:$B$10, 2, FALSE), 0)) | P22: =IF(E22="HERRAJE", A22*O22, M22*O22) | Q22: =IF(E22="HERRAJE", 0, IFERROR(VLOOKUP(E22, '⚙️ Configuración Costos'!$E$5:$F$10, 2, FALSE), 0)) | R22: =N22*Q22 | S22: =P22+R22
A23: 4 | B23: 175 | C23: 496 | D23: Frente de Cajón | E23: MADERADO FRENTE | F23: 1 | G23: 1 | H23: 1 | I23: 1 | J23: 1 | K23: MOD-CAJ-01 | L23: MOD-CAJ-01-P05 | M23: =IF(AND(ISNUMBER(B23), B23>0), (A23*B23*C23)/1000000, 0) | N23: =IF(AND(ISNUMBER(B23), B23>0), A23*(((G23+H23)*B23 + (I23+J23)*C23)/1000), 0) | O23: =IF(E23="HERRAJE", IFERROR(VLOOKUP(D23, '⚙️ Configuración Costos'!$A$13:$B$30, 2, FALSE), 0), IFERROR(VLOOKUP(E23, '⚙️ Configuración Costos'!$A$5:$B$10, 2, FALSE), 0)) | P23: =IF(E23="HERRAJE", A23*O23, M23*O23) | Q23: =IF(E23="HERRAJE", 0, IFERROR(VLOOKUP(E23, '⚙️ Configuración Costos'!$E$5:$F$10, 2, FALSE), 0)) | R23: =N23*Q23 | S23: =P23+R23
A24: 8 | B24: 500 | C24: 120 | D24: Lateral de Cajón | E24: ARAUCO BLANCO | F24: 0 | G24: 1 | H24: 0 | I24: 0 | J24: 0 | K24: MOD-CAJ-01 | L24: MOD-CAJ-01-P06 | M24: =IF(AND(ISNUMBER(B24), B24>0), (A24*B24*C24)/1000000, 0) | N24: =IF(AND(ISNUMBER(B24), B24>0), A24*(((G24+H24)*B24 + (I24+J24)*C24)/1000), 0) | O24: =IF(E24="HERRAJE", IFERROR(VLOOKUP(D24, '⚙️ Configuración Costos'!$A$13:$B$30, 2, FALSE), 0), IFERROR(VLOOKUP(E24, '⚙️ Configuración Costos'!$A$5:$B$10, 2, FALSE), 0)) | P24: =IF(E24="HERRAJE", A24*O24, M24*O24) | Q24: =IF(E24="HERRAJE", 0, IFERROR(VLOOKUP(E24, '⚙️ Configuración Costos'!$E$5:$F$10, 2, FALSE), 0)) | R24: =N24*Q24 | S24: =P24+R24
A25: 4 | B25: 412 | C25: 120 | D25: Frente/Tras Cajón | E25: ARAUCO BLANCO | F25: 0 | G25: 1 | H25: 0 | I25: 0 | J25: 0 | K25: MOD-CAJ-01 | L25: MOD-CAJ-01-P07 | M25: =IF(AND(ISNUMBER(B25), B25>0), (A25*B25*C25)/1000000, 0) | N25: =IF(AND(ISNUMBER(B25), B25>0), A25*(((G25+H25)*B25 + (I25+J25)*C25)/1000), 0) | O25: =IF(E25="HERRAJE", IFERROR(VLOOKUP(D25, '⚙️ Configuración Costos'!$A$13:$B$30, 2, FALSE), 0), IFERROR(VLOOKUP(E25, '⚙️ Configuración Costos'!$A$5:$B$10, 2, FALSE), 0)) | P25: =IF(E25="HERRAJE", A25*O25, M25*O25) | Q25: =IF(E25="HERRAJE", 0, IFERROR(VLOOKUP(E25, '⚙️ Configuración Costos'!$E$5:$F$10, 2, FALSE), 0)) | R25: =N25*Q25 | S25: =P25+R25
A26: 4 | B26: 500 | C26: 442 | D26: Fondo de Cajón (MDF) | E26: MDF 3MM | F26: 0 | G26: 0 | H26: 0 | I26: 0 | J26: 0 | K26: MOD-CAJ-01 | L26: MOD-CAJ-01-P08 | M26: =IF(AND(ISNUMBER(B26), B26>0), (A26*B26*C26)/1000000, 0) | N26: =IF(AND(ISNUMBER(B26), B26>0), A26*(((G26+H26)*B26 + (I26+J26)*C26)/1000), 0) | O26: =IF(E26="HERRAJE", IFERROR(VLOOKUP(D26, '⚙️ Configuración Costos'!$A$13:$B$30, 2, FALSE), 0), IFERROR(VLOOKUP(E26, '⚙️ Configuración Costos'!$A$5:$B$10, 2, FALSE), 0)) | P26: =IF(E26="HERRAJE", A26*O26, M26*O26) | Q26: =IF(E26="HERRAJE", 0, IFERROR(VLOOKUP(E26, '⚙️ Configuración Costos'!$E$5:$F$10, 2, FALSE), 0)) | R26: =N26*Q26 | S26: =P26+R26
A27: 4 | B27: 0 | C27: 0 | D27: Corredera Telescópica 500mm | E27: HERRAJE | F27: 0 | G27: 0 | H27: 0 | I27: 0 | J27: 0 | K27: MOD-CAJ-01 | L27: MOD-CAJ-01-H01 | M27: =IF(AND(ISNUMBER(B27), B27>0), (A27*B27*C27)/1000000, 0) | N27: =IF(AND(ISNUMBER(B27), B27>0), A27*(((G27+H27)*B27 + (I27+J27)*C27)/1000), 0) | O27: =IF(E27="HERRAJE", IFERROR(VLOOKUP(D27, '⚙️ Configuración Costos'!$A$13:$B$30, 2, FALSE), 0), IFERROR(VLOOKUP(E27, '⚙️ Configuración Costos'!$A$5:$B$10, 2, FALSE), 0)) | P27: =IF(E27="HERRAJE", A27*O27, M27*O27) | Q27: =IF(E27="HERRAJE", 0, IFERROR(VLOOKUP(E27, '⚙️ Configuración Costos'!$E$5:$F$10, 2, FALSE), 0)) | R27: =N27*Q27 | S27: =P27+R27
A28: 4 | B28: 0 | C28: 0 | D28: Jaladera Acero Inox | E28: HERRAJE | F28: 0 | G28: 0 | H28: 0 | I28: 0 | J28: 0 | K28: MOD-CAJ-01 | L28: MOD-CAJ-01-H02 | M28: =IF(AND(ISNUMBER(B28), B28>0), (A28*B28*C28)/1000000, 0) | N28: =IF(AND(ISNUMBER(B28), B28>0), A28*(((G28+H28)*B28 + (I28+J28)*C28)/1000), 0) | O28: =IF(E28="HERRAJE", IFERROR(VLOOKUP(D28, '⚙️ Configuración Costos'!$A$13:$B$30, 2, FALSE), 0), IFERROR(VLOOKUP(E28, '⚙️ Configuración Costos'!$A$5:$B$10, 2, FALSE), 0)) | P28: =IF(E28="HERRAJE", A28*O28, M28*O28) | Q28: =IF(E28="HERRAJE", 0, IFERROR(VLOOKUP(E28, '⚙️ Configuración Costos'!$E$5:$F$10, 2, FALSE), 0)) | R28: =N28*Q28 | S28: =P28+R28
A29: 4 | B29: 0 | C29: 0 | D29: Pata Regulable Plastica | E29: HERRAJE | F29: 0 | G29: 0 | H29: 0 | I29: 0 | J29: 0 | K29: MOD-CAJ-01 | L29: MOD-CAJ-01-H03 | M29: =IF(AND(ISNUMBER(B29), B29>0), (A29*B29*C29)/1000000, 0) | N29: =IF(AND(ISNUMBER(B29), B29>0), A29*(((G29+H29)*B29 + (I29+J29)*C29)/1000), 0) | O29: =IF(E29="HERRAJE", IFERROR(VLOOKUP(D29, '⚙️ Configuración Costos'!$A$13:$B$30, 2, FALSE), 0), IFERROR(VLOOKUP(E29, '⚙️ Configuración Costos'!$A$5:$B$10, 2, FALSE), 0)) | P29: =IF(E29="HERRAJE", A29*O29, M29*O29) | Q29: =IF(E29="HERRAJE", 0, IFERROR(VLOOKUP(E29, '⚙️ Configuración Costos'!$E$5:$F$10, 2, FALSE), 0)) | R29: =N29*Q29 | S29: =P29+R29
A30: 60 | B30: 0 | C30: 0 | D30: Tornillo 4x50 mm | E30: HERRAJE | F30: 0 | G30: 0 | H30: 0 | I30: 0 | J30: 0 | K30: MOD-CAJ-01 | L30: MOD-CAJ-01-H04 | M30: =IF(AND(ISNUMBER(B30), B30>0), (A30*B30*C30)/1000000, 0) | N30: =IF(AND(ISNUMBER(B30), B30>0), A30*(((G30+H30)*B30 + (I30+J30)*C30)/1000), 0) | O30: =IF(E30="HERRAJE", IFERROR(VLOOKUP(D30, '⚙️ Configuración Costos'!$A$13:$B$30, 2, FALSE), 0), IFERROR(VLOOKUP(E30, '⚙️ Configuración Costos'!$A$5:$B$10, 2, FALSE), 0)) | P30: =IF(E30="HERRAJE", A30*O30, M30*O30) | Q30: =IF(E30="HERRAJE", 0, IFERROR(VLOOKUP(E30, '⚙️ Configuración Costos'!$E$5:$F$10, 2, FALSE), 0)) | R30: =N30*Q30 | S30: =P30+R30
D31: TOTAL DEL CATÁLOGO / PROYECTO | P31: =SUM(P4:P30) | R31: =SUM(R4:R30) | S31: =SUM(S4:S30)

Sheet ⚙️ Configuración Costos
A1: CONFIGURACIÓN DE COSTOS DE MATERIALES Y HERRAJES
A3: Tableros (Costo por M²) | E3: Cintillas / Cantos (Costo por ML)
A4: Materia Prima | B4: Costo por M² (MXN) | C4: Descripción / Notas | E4: Materia Prima | F4: Costo por ML (MXN) | G4: Espesor / Tipo
A5: ARAUCO BLANCO | B5: 160 | C5: Melamina blanca estándar 15/18mm | E5: ARAUCO BLANCO | F5: 12 | G5: Canto PVC delgado 0.5mm
A6: MADERADO FRENTE | B6: 290 | C6: Melamina texturizada premium para frentes | E6: MADERADO FRENTE | F6: 25 | G6: Canto PVC grueso 2mm
A7: MDF 3MM | B7: 75 | C7: Fondo de cajones y respaldos delgados | E7: MDF 3MM | F7: 0 | G7: Sin canto
A8: HERRAJE | B8: 0 | C8: Comodín para fila de herrajes (No modificar) | E8: HERRAJE | F8: 0 | G8: Sin canto
A11: Herrajes y Accesorios (Costo por Unidad)
A12: Descripción del Herraje | B12: Costo Unitario (MXN) | C12: Unidad de Medida
A13: Bisagra Cierre Lento | B13: 35 | C13: Pieza
A14: Jaladera Acero Inox | B14: 45 | C14: Pieza
A15: Pata Regulable Plastica | B15: 15 | C15: Pieza
A16: Tornillo 4x50 mm | B16: 0.5 | C16: Pieza
A17: Corredera Telescópica 500mm | B17: 120 | C17: Juego
A18: Soporte de Entrepaño | B18: 2 | C18: Pieza
